pyPilot/__init__.py
pyPilot/coordinate.py
pyPilot/earth.py
pyPilot/inputs.py
pyPilot/pilotUtils.py
pyPilot/pose.py
pyPilot/rotation.py
pyPilot/wgs84.py
pyPilot-0.2.1.dist-info/LICENSE
pyPilot-0.2.1.dist-info/METADATA
pyPilot-0.2.1.dist-info/WHEEL
pyPilot-0.2.1.dist-info/top_level.txt
pyPilot-0.2.1.dist-info/RECORD
