Metadata-Version: 2.1
Name: pyPilot
Version: 0.2.1
Summary: Python package for navigation, guidance, path planning, and control
Home-page: https://github.com/PowerBroker2/pyPilot
Download-URL: https://github.com/PowerBroker2/pyPilot/archive/0.2.1.tar.gz
Author: Power_Broker
Author-email: gitstuff2@gmail.com
License: UNKNOWN
Keywords: pyPilot
Platform: UNKNOWN
License-File: LICENSE
Requires-Dist: numpy
Requires-Dist: scipy
